{"nodes": [{"id": "app_services", "label": "app-services.ts", "file_type": "code", "source_file": "src/app-setup/app-services.ts", "source_location": "L1"}], "edges": [{"source": "app_services", "target": "fastify", "relation": "imports_from", "confidence": "EXTRACTED", "source_file": "src/app-setup/app-services.ts", "source_location": "L7", "weight": 1.0}, {"source": "app_services", "target": "pg", "relation": "imports_from", "confidence": "EXTRACTED", "source_file": "src/app-setup/app-services.ts", "source_location": "L8", "weight": 1.0}, {"source": "app_services", "target": "app_context_js", "relation": "imports_from", "confidence": "EXTRACTED", "source_file": "src/app-setup/app-services.ts", "source_location": "L9", "weight": 1.0}, {"source": "app_services", "target": "runtime_config_js", "relation": "imports_from", "confidence": "EXTRACTED", "source_file": "src/app-setup/app-services.ts", "source_location": "L10", "weight": 1.0}, {"source": "app_services", "target": "types_js", "relation": "imports_from", "confidence": "EXTRACTED", "source_file": "src/app-setup/app-services.ts", "source_location": "L11", "weight": 1.0}, {"source": "app_services", "target": "hot_trend_base_js", "relation": "imports_from", "confidence": "EXTRACTED", "source_file": "src/app-setup/app-services.ts", "source_location": "L20", "weight": 1.0}, {"source": "app_services", "target": "video_job_runtime_js", "relation": "imports_from", "confidence": "EXTRACTED", "source_file": "src/app-setup/app-services.ts", "source_location": "L21", "weight": 1.0}, {"source": "app_services", "target": "provider_route_contract_js", "relation": "imports_from", "confidence": "EXTRACTED", "source_file": "src/app-setup/app-services.ts", "source_location": "L22", "weight": 1.0}, {"source": "app_services", "target": "video_reverse_analysis_service_js", "relation": "imports_from", "confidence": "EXTRACTED", "source_file": "src/app-setup/app-services.ts", "source_location": "L23", "weight": 1.0}, {"source": "app_services", "target": "outfit_analysis_helpers_js", "relation": "imports_from", "confidence": "EXTRACTED", "source_file": "src/app-setup/app-services.ts", "source_location": "L24", "weight": 1.0}, {"source": "app_services", "target": "step1_joint_reverse_contract_js", "relation": "imports_from", "confidence": "EXTRACTED", "source_file": "src/app-setup/app-services.ts", "source_location": "L25", "weight": 1.0}, {"source": "app_services", "target": "error_log_service_js", "relation": "imports_from", "confidence": "EXTRACTED", "source_file": "src/app-setup/app-services.ts", "source_location": "L26", "weight": 1.0}, {"source": "app_services", "target": "error_log_queue_js", "relation": "imports_from", "confidence": "EXTRACTED", "source_file": "src/app-setup/app-services.ts", "source_location": "L27", "weight": 1.0}, {"source": "app_services", "target": "error_log_cleanup_scheduler_js", "relation": "imports_from", "confidence": "EXTRACTED", "source_file": "src/app-setup/app-services.ts", "source_location": "L28", "weight": 1.0}, {"source": "app_services", "target": "setup_hot_trend_js", "relation": "imports_from", "confidence": "EXTRACTED", "source_file": "src/app-setup/app-services.ts", "source_location": "L156", "weight": 1.0}]}